Workbook

Sheet Dashboard
A1: ISCC Active Certificates — Interactive Dashboard
B3: Total Active Certificates | C3: 16325 | E3: Countries | F3: 146
B5: Select Country: | C5: China | E5: Select CB: | F5: SGS Germany GmbH, Emstek, DE
B6: Total certificates: | C6: =COUNTIF(CertData[Country],$C$5)
B7: Certification Body | C7: Count | E7: Country | F7: Count
B8: =IFERROR(INDEX(CB_Data!$B:$B,MATCH($C$5,CB_Data!$A:$A,0)+0),"") | C8: =IFERROR(IF(INDEX(CB_Data!$C:$C,MATCH($C$5,CB_Data!$A:$A,0)+0)=0,NA(),INDEX(CB_Data!$C:$C,MATCH($C$5,CB_Data!$A:$A,0)+0)),NA()) | E8: =IFERROR(INDEX(Country_Data!$B:$B,MATCH($F$5,Country_Data!$A:$A,0)+0),"") | F8: =IFERROR(IF(INDEX(Country_Data!$C:$C,MATCH($F$5,Country_Data!$A:$A,0)+0)=0,NA(),INDEX(Country_Data!$C:$C,MATCH($F$5,Country_Data!$A:$A,0)+0)),NA())
B9: =IFERROR(INDEX(CB_Data!$B:$B,MATCH($C$5,CB_Data!$A:$A,0)+1),"") | C9: =IFERROR(IF(INDEX(CB_Data!$C:$C,MATCH($C$5,CB_Data!$A:$A,0)+1)=0,NA(),INDEX(CB_Data!$C:$C,MATCH($C$5,CB_Data!$A:$A,0)+1)),NA()) | E9: =IFERROR(INDEX(Country_Data!$B:$B,MATCH($F$5,Country_Data!$A:$A,0)+1),"") | F9: =IFERROR(IF(INDEX(Country_Data!$C:$C,MATCH($F$5,Country_Data!$A:$A,0)+1)=0,NA(),INDEX(Country_Data!$C:$C,MATCH($F$5,Country_Data!$A:$A,0)+1)),NA())
B10: =IFERROR(INDEX(CB_Data!$B:$B,MATCH($C$5,CB_Data!$A:$A,0)+2),"") | C10: =IFERROR(IF(INDEX(CB_Data!$C:$C,MATCH($C$5,CB_Data!$A:$A,0)+2)=0,NA(),INDEX(CB_Data!$C:$C,MATCH($C$5,CB_Data!$A:$A,0)+2)),NA()) | E10: =IFERROR(INDEX(Country_Data!$B:$B,MATCH($F$5,Country_Data!$A:$A,0)+2),"") | F10: =IFERROR(IF(INDEX(Country_Data!$C:$C,MATCH($F$5,Country_Data!$A:$A,0)+2)=0,NA(),INDEX(Country_Data!$C:$C,MATCH($F$5,Country_Data!$A:$A,0)+2)),NA())
B11: =IFERROR(INDEX(CB_Data!$B:$B,MATCH($C$5,CB_Data!$A:$A,0)+3),"") | C11: =IFERROR(IF(INDEX(CB_Data!$C:$C,MATCH($C$5,CB_Data!$A:$A,0)+3)=0,NA(),INDEX(CB_Data!$C:$C,MATCH($C$5,CB_Data!$A:$A,0)+3)),NA()) | E11: =IFERROR(INDEX(Country_Data!$B:$B,MATCH($F$5,Country_Data!$A:$A,0)+3),"") | F11: =IFERROR(IF(INDEX(Country_Data!$C:$C,MATCH($F$5,Country_Data!$A:$A,0)+3)=0,NA(),INDEX(Country_Data!$C:$C,MATCH($F$5,Country_Data!$A:$A,0)+3)),NA())
B12: =IFERROR(INDEX(CB_Data!$B:$B,MATCH($C$5,CB_Data!$A:$A,0)+4),"") | C12: =IFERROR(IF(INDEX(CB_Data!$C:$C,MATCH($C$5,CB_Data!$A:$A,0)+4)=0,NA(),INDEX(CB_Data!$C:$C,MATCH($C$5,CB_Data!$A:$A,0)+4)),NA()) | E12: =IFERROR(INDEX(Country_Data!$B:$B,MATCH($F$5,Country_Data!$A:$A,0)+4),"") | F12: =IFERROR(IF(INDEX(Country_Data!$C:$C,MATCH($F$5,Country_Data!$A:$A,0)+4)=0,NA(),INDEX(Country_Data!$C:$C,MATCH($F$5,Country_Data!$A:$A,0)+4)),NA())
B13: =IFERROR(INDEX(CB_Data!$B:$B,MATCH($C$5,CB_Data!$A:$A,0)+5),"") | C13: =IFERROR(IF(INDEX(CB_Data!$C:$C,MATCH($C$5,CB_Data!$A:$A,0)+5)=0,NA(),INDEX(CB_Data!$C:$C,MATCH($C$5,CB_Data!$A:$A,0)+5)),NA()) | E13: =IFERROR(INDEX(Country_Data!$B:$B,MATCH($F$5,Country_Data!$A:$A,0)+5),"") | F13: =IFERROR(IF(INDEX(Country_Data!$C:$C,MATCH($F$5,Country_Data!$A:$A,0)+5)=0,NA(),INDEX(Country_Data!$C:$C,MATCH($F$5,Country_Data!$A:$A,0)+5)),NA())
B14: =IFERROR(INDEX(CB_Data!$B:$B,MATCH($C$5,CB_Data!$A:$A,0)+6),"") | C14: =IFERROR(IF(INDEX(CB_Data!$C:$C,MATCH($C$5,CB_Data!$A:$A,0)+6)=0,NA(),INDEX(CB_Data!$C:$C,MATCH($C$5,CB_Data!$A:$A,0)+6)),NA()) | E14: =IFERROR(INDEX(Country_Data!$B:$B,MATCH($F$5,Country_Data!$A:$A,0)+6),"") | F14: =IFERROR(IF(INDEX(Country_Data!$C:$C,MATCH($F$5,Country_Data!$A:$A,0)+6)=0,NA(),INDEX(Country_Data!$C:$C,MATCH($F$5,Country_Data!$A:$A,0)+6)),NA())
B15: =IFERROR(INDEX(CB_Data!$B:$B,MATCH($C$5,CB_Data!$A:$A,0)+7),"") | C15: =IFERROR(IF(INDEX(CB_Data!$C:$C,MATCH($C$5,CB_Data!$A:$A,0)+7)=0,NA(),INDEX(CB_Data!$C:$C,MATCH($C$5,CB_Data!$A:$A,0)+7)),NA()) | E15: =IFERROR(INDEX(Country_Data!$B:$B,MATCH($F$5,Country_Data!$A:$A,0)+7),"") | F15: =IFERROR(IF(INDEX(Country_Data!$C:$C,MATCH($F$5,Country_Data!$A:$A,0)+7)=0,NA(),INDEX(Country_Data!$C:$C,MATCH($F$5,Country_Data!$A:$A,0)+7)),NA())
B16: =IFERROR(INDEX(CB_Data!$B:$B,MATCH($C$5,CB_Data!$A:$A,0)+8),"") | C16: =IFERROR(IF(INDEX(CB_Data!$C:$C,MATCH($C$5,CB_Data!$A:$A,0)+8)=0,NA(),INDEX(CB_Data!$C:$C,MATCH($C$5,CB_Data!$A:$A,0)+8)),NA()) | E16: =IFERROR(INDEX(Country_Data!$B:$B,MATCH($F$5,Country_Data!$A:$A,0)+8),"") | F16: =IFERROR(IF(INDEX(Country_Data!$C:$C,MATCH($F$5,Country_Data!$A:$A,0)+8)=0,NA(),INDEX(Country_Data!$C:$C,MATCH($F$5,Country_Data!$A:$A,0)+8)),NA())
B17: =IFERROR(INDEX(CB_Data!$B:$B,MATCH($C$5,CB_Data!$A:$A,0)+9),"") | C17: =IFERROR(IF(INDEX(CB_Data!$C:$C,MATCH($C$5,CB_Data!$A:$A,0)+9)=0,NA(),INDEX(CB_Data!$C:$C,MATCH($C$5,CB_Data!$A:$A,0)+9)),NA()) | E17: =IFERROR(INDEX(Country_Data!$B:$B,MATCH($F$5,Country_Data!$A:$A,0)+9),"") | F17: =IFERROR(IF(INDEX(Country_Data!$C:$C,MATCH($F$5,Country_Data!$A:$A,0)+9)=0,NA(),INDEX(Country_Data!$C:$C,MATCH($F$5,Country_Data!$A:$A,0)+9)),NA())

Sheet CB_Data
A1: Country | B1: CB | C1: Count
A2: China | B2: SCS Global Services, Emeryville, CA, US | C2: 646
A3: China | B3: RINA Services S.p.A., Genova, IT | C3: 573
A4: China | B4: SGS Germany GmbH, Emstek, DE | C4: 243
A5: China | B5: PT Intertek Utama Services, Jakarta, ID | C5: 110
A6: China | B6: CTI Certification Co. Ltd, Shenzhen, CN | C6: 91
A7: China | B7: China Quality Certification Centre Co., Ltd., Beijing, CN | C7: 87
A8: China | B8: Bureau Veritas Polska Sp. z o.o., Warsaw, PL | C8: 84
A9: China | B9: DIN CERTCO GmbH, Berlin, DE | C9: 80
A10: China | B10: Extensive Standard Technical Services Co., Ltd., Hong Kong, CN | C10: 49
A11: China | B11: TÜV NORD CERT GmbH, Essen, DE | C11: 46
A12: United States | B12: SCS Global Services, Emeryville, CA, US | C12: 575
A13: United States | B13: Control Union Poland Sp. z o.o., Zielona Gora, PL | C13: 99
... A190: Brazil | B190: Baltic Control Certification, Albertslund, DK | C190: 1
A191: Brazil | C191: 0
A192: India | B192: Cotecna India Inspection Pvt Ltd, Kolkata, IN | C192: 80
A193: India | B193: SGS Germany GmbH, Emstek, DE | C193: 32
A194: India | B194: Alcumus ISOQAR Ltd, Stretford, Manchester, GB | C194: 26
A195: India | B195: PT Intertek Utama Services, Jakarta, ID | C195: 21
A196: India | B196: ISOQAR Ltd, Stretford, Manchester, GB | C196: 20
A197: India | B197: Control Union Certifications Germany GmbH, Berlin, DE | C197: 11
A198: India | B198: TÜV SÜD Industrie Service GmbH, München, DE | C198: 5
A199: India | B199: Trans Certification and Inspection Sdn Bhd, Kuantan, MY | C199: 5
A200: India | B200: SCS Global Services, Emeryville, CA, US | C200: 4
A201: India | B201: RINA Services S.p.A., Genova, IT | C201: 4
A202: Switzerland | B202: SGS Germany GmbH, Emstek, DE | C202: 65
A203: Switzerland | B203: Control Union Certifications Germany GmbH, Berlin, DE | C203: 31
... A230: Republic of | B230: PT Intertek Utama Services, Jakarta, ID | C230: 1
A231: Republic of | C231: 0
A232: Thailand | B232: SGS Germany GmbH, Emstek, DE | C232: 67
A233: Thailand | B233: Control Union Poland Sp. z o.o., Zielona Gora, PL | C233: 43
A234: Thailand | B234: Trans Certification and Inspection Sdn Bhd, Kuantan, MY | C234: 24
A235: Thailand | B235: Bureau Veritas Polska Sp. z o.o., Warsaw, PL | C235: 21
A236: Thailand | B236: SCS Global Services, Emeryville, CA, US | C236: 9
A237: Thailand | B237: PT Intertek Utama Services, Jakarta, ID | C237: 7
A238: Thailand | B238: PT. CBQA GLOBAL INDONESIA, JAKARTA SELATAN, ID | C238: 6
A239: Thailand | B239: TÜV NORD CERT GmbH, Essen, DE | C239: 3
A240: Thailand | B240: China Testing & Certification International Group Co., Ltd., Beijing, CN | C240: 3
A241: Thailand | B241: PT. Qualitas Sertifikasi Indonesia, Jakarta, ID | C241: 2
A242: South Korea | B242: Control Union Certifications Germany GmbH, Berlin, DE | C242: 95
A243: South Korea | B243: Korean Foundation for Quality, Songpa-gu, Seoul, KR | C243: 53
... A288: Australia | B288: PT Mutuagung Lestari, Depok, ID | C288: 1
A289: Australia | C289: 0
A290: Australia | C290: 0
A291: Australia | C291: 0
A292: Sweden | B292: DNV Business Assurance Sweden AB, Solna, SE | C292: 67
A293: Sweden | B293: Bureau Veritas Polska Sp. z o.o., Warsaw, PL | C293: 17
A294: Sweden | B294: SGS Germany GmbH, Emstek, DE | C294: 16
A295: Sweden | B295: DEKRA Certification B.V., Arnhem, NL | C295: 11
A296: Sweden | B296: SCS Global Services, Emeryville, CA, US | C296: 10
A297: Sweden | B297: ASG Cert GmbH, Munich, DE | C297: 6
A298: Sweden | B298: PT Intertek Utama Services, Jakarta, ID | C298: 3
A299: Sweden | B299: DIN CERTCO GmbH, Berlin, DE | C299: 2
A300: Sweden | B300: TÜV SÜD Industrie Service GmbH, München, DE | C300: 2
A301: Sweden | B301: Double Helix Tracking Technologies Pte Ltd, Singapore, SG | C301: 2
A302: Canada | B302: SCS Global Services, Emeryville, CA, US | C302: 55
A303: Canada | B303: SGS Germany GmbH, Emstek, DE | C303: 40
... A318: Greece | B318: SGS Germany GmbH, Emstek, DE | C318: 1
A319: Greece | C319: 0
A320: Greece | C320: 0
A321: Greece | C321: 0
A322: The Netherlands | B322: DEKRA Certification B.V., Arnhem, NL | C322: 53
A323: The Netherlands | B323: Normec QS BV, Ede, NL | C323: 23
A324: The Netherlands | B324: SGS Germany GmbH, Emstek, DE | C324: 17
A325: The Netherlands | B325: Control Union Certifications Germany GmbH, Berlin, DE | C325: 17
A326: The Netherlands | B326: Normec QS BV, Bennekom, NL | C326: 7
A327: The Netherlands | B327: DQS CFS GmbH - Deutsche Gesellschaft für Nachhaltigkeit, Frankfurt am Main, DE | C327: 4
A328: The Netherlands | B328: Double Helix Tracking Technologies Pte Ltd, Singapore, SG | C328: 2
A329: The Netherlands | B329: GUT Certifizierungsgesellschaft für Managementsysteme mbH Umweltgutachter, Berlin, DE | C329: 2
A330: The Netherlands | B330: TÜV NORD CERT GmbH, Essen, DE | C330: 2
A331: The Netherlands | B331: ASG Cert GmbH, Munich, DE | C331: 2
A332: Portugal | B332: SGS Germany GmbH, Emstek, DE | C332: 35
A333: Portugal | B333: Control Union Poland Sp. z o.o., Zielona Gora, PL | C333: 33
... A358: Lithuania | B358: TÜV NORD CERT GmbH, Essen, DE | C358: 1
A359: Lithuania | C359: 0
A360: Lithuania | C360: 0
A361: Lithuania | C361: 0
A362: Turkey | B362: PT Intertek Utama Services, Jakarta, ID | C362: 33
A363: Turkey | B363: BM Certification, Riga, LV | C363: 16
A364: Turkey | B364: RINA Services S.p.A., Genova, IT | C364: 13
A365: Turkey | B365: Trans Certification and Inspection Sdn Bhd, Kuantan, MY | C365: 12
A366: Turkey | B366: Bureau Veritas Polska Sp. z o.o., Warsaw, PL | C366: 7
A367: Turkey | B367: Control Union Certifications Germany GmbH, Berlin, DE | C367: 6
A368: Turkey | B368: Certificadora Gallega del Noroeste SL, Vilagarcia de Arousa-Pontevedra, ES | C368: 6
A369: Turkey | B369: Business Quality Verification Testing and Certification Services P.C. (BQV), Marousi, Athens, GR | C369: 4
A370: Turkey | B370: ASG Cert GmbH, Munich, DE | C370: 2
A371: Turkey | B371: Control Union Poland Sp. z o.o., Zielona Gora, PL | C371: 2
A372: Finland | B372: DNV Business Assurance Sweden AB, Solna, SE | C372: 30
A373: Finland | B373: SGS Germany GmbH, Emstek, DE | C373: 15
... A389: Argentina | B389: SCS Global Services, Emeryville, CA, US | C389: 1
A390: Argentina | C390: 0
A391: Argentina | C391: 0
A392: The Republic of Korea | B392: Control Union Certifications Germany GmbH, Berlin, DE | C392: 65
A393: The Republic of Korea | B393: Korean Foundation for Quality, Songpa-gu, Seoul, KR | C393: 8
A394: The Republic of Korea | B394: SGS Germany GmbH, Emstek, DE | C394: 5
A395: The Republic of Korea | B395: BM Certification, Riga, LV | C395: 4
A396: The Republic of Korea | B396: PT Intertek Utama Services, Jakarta, ID | C396: 2
A397: The Republic of Korea | B397: FITI Testing & Research Institute, Seoul, KR | C397: 1
A398: The Republic of Korea | B398: Bureau Veritas Polska Sp. z o.o., Warsaw, PL | C398: 1
A399: The Republic of Korea | C399: 0
...

Sheet Country_Data
A1: CB | B1: Country | C1: Count
A2: SGS Germany GmbH, Emstek, DE | B2: Japan | C2: 300
A3: SGS Germany GmbH, Emstek, DE | B3: China | C3: 243
A4: SGS Germany GmbH, Emstek, DE | B4: Italy | C4: 192
A5: SGS Germany GmbH, Emstek, DE | B5: Germany | C5: 166
A6: SGS Germany GmbH, Emstek, DE | B6: United Kingdom | C6: 100
A7: SGS Germany GmbH, Emstek, DE | B7: Indonesia | C7: 94
A8: SGS Germany GmbH, Emstek, DE | B8: Netherlands | C8: 82
A9: SGS Germany GmbH, Emstek, DE | B9: Belgium | C9: 77
A10: SGS Germany GmbH, Emstek, DE | B10: Romania | C10: 76
A11: SGS Germany GmbH, Emstek, DE | B11: Thailand | C11: 67
A12: Control Union Certifications Germany GmbH, Berlin, DE | B12: Japan | C12: 195
A13: Control Union Certifications Germany GmbH, Berlin, DE | B13: Republic of | C13: 175
... A255: SRAC Cert SRL, Bucharest, RO | B255: Montenegro | C255: 1
A256: SRAC Cert SRL, Bucharest, RO | C256: 0
A257: SRAC Cert SRL, Bucharest, RO | C257: 0
A258: SRAC Cert SRL, Bucharest, RO | C258: 0
A259: SRAC Cert SRL, Bucharest, RO | C259: 0
A260: SRAC Cert SRL, Bucharest, RO | C260: 0
A261: SRAC Cert SRL, Bucharest, RO | C261: 0
A262: Aardvark Certification Ltd, Wiveliscombe, Somerset, GB | B262: United Kingdom | C262: 60
A263: Aardvark Certification Ltd, Wiveliscombe, Somerset, GB | B263: The United Kingdom | C263: 15
A264: Aardvark Certification Ltd, Wiveliscombe, Somerset, GB | B264: Ireland | C264: 15
A265: Aardvark Certification Ltd, Wiveliscombe, Somerset, GB | B265: France | C265: 4
A266: Aardvark Certification Ltd, Wiveliscombe, Somerset, GB | B266: South Africa | C266: 3
A267: Aardvark Certification Ltd, Wiveliscombe, Somerset, GB | B267: Germany | C267: 3
A268: Aardvark Certification Ltd, Wiveliscombe, Somerset, GB | B268: United States | C268: 2
A269: Aardvark Certification Ltd, Wiveliscombe, Somerset, GB | B269: Malaysia | C269: 2
A270: Aardvark Certification Ltd, Wiveliscombe, Somerset, GB | B270: The United States of America | C270: 1
A271: Aardvark Certification Ltd, Wiveliscombe, Somerset, GB | B271: Egypt | C271: 1
A272: ICIM SpA, sesto san giovanni, IT | B272: Italy | C272: 79
A273: ICIM SpA, sesto san giovanni, IT | B273: Panama | C273: 7
... A284: CTI Certification Co. Ltd, Shenzhen, CN | B284: Vietnam | C284: 1
A285: CTI Certification Co. Ltd, Shenzhen, CN | C285: 0
A286: CTI Certification Co. Ltd, Shenzhen, CN | C286: 0
A287: CTI Certification Co. Ltd, Shenzhen, CN | C287: 0
A288: CTI Certification Co. Ltd, Shenzhen, CN | C288: 0
A289: CTI Certification Co. Ltd, Shenzhen, CN | C289: 0
A290: CTI Certification Co. Ltd, Shenzhen, CN | C290: 0
A291: CTI Certification Co. Ltd, Shenzhen, CN | C291: 0
A292: China Quality Certification Centre Co., Ltd., Beijing, CN | B292: China | C292: 87
A293: China Quality Certification Centre Co., Ltd., Beijing, CN | B293: Vietnam | C293: 6
A294: China Quality Certification Centre Co., Ltd., Beijing, CN | B294: Indonesia | C294: 3
A295: China Quality Certification Centre Co., Ltd., Beijing, CN | B295: Hong Kong | C295: 2
A296: China Quality Certification Centre Co., Ltd., Beijing, CN | B296: Province of China | C296: 2
A297: China Quality Certification Centre Co., Ltd., Beijing, CN | B297: Taiwan | C297: 1
A298: China Quality Certification Centre Co., Ltd., Beijing, CN | C298: 0
A299: China Quality Certification Centre Co., Ltd., Beijing, CN | C299: 0
A300: China Quality Certification Centre Co., Ltd., Beijing, CN | C300: 0
A301: China Quality Certification Centre Co., Ltd., Beijing, CN | C301: 0
A302: PT SBC Asia Sertifikasi, Kebumen, ID | B302: Indonesia | C302: 71
A303: PT SBC Asia Sertifikasi, Kebumen, ID | B303: Malaysia | C303: 15
A304: PT SBC Asia Sertifikasi, Kebumen, ID | B304: Singapore | C304: 7
A305: PT SBC Asia Sertifikasi, Kebumen, ID | B305: United Arab Emirates | C305: 2
A306: PT SBC Asia Sertifikasi, Kebumen, ID | B306: Philippines | C306: 1
A307: PT SBC Asia Sertifikasi, Kebumen, ID | B307: China | C307: 1
A308: PT SBC Asia Sertifikasi, Kebumen, ID | B308: Germany | C308: 1
A309: PT SBC Asia Sertifikasi, Kebumen, ID | B309: Türkiye | C309: 1
A310: PT SBC Asia Sertifikasi, Kebumen, ID | C310: 0
A311: PT SBC Asia Sertifikasi, Kebumen, ID | C311: 0
A312: Cotecna India Inspection Pvt Ltd, Kolkata, IN | B312: India | C312: 80
A313: Cotecna India Inspection Pvt Ltd, Kolkata, IN | B313: Saudi Arabia | C313: 5
A314: Cotecna India Inspection Pvt Ltd, Kolkata, IN | B314: United Arab Emirates | C314: 4
A315: Cotecna India Inspection Pvt Ltd, Kolkata, IN | B315: South Africa | C315: 2
A316: Cotecna India Inspection Pvt Ltd, Kolkata, IN | B316: Egypt | C316: 2
A317: Cotecna India Inspection Pvt Ltd, Kolkata, IN | B317: Thailand | C317: 1
A318: Cotecna India Inspection Pvt Ltd, Kolkata, IN | B318: Oman | C318: 1
A319: Cotecna India Inspection Pvt Ltd, Kolkata, IN | B319: United Kingdom | C319: 1
A320: Cotecna India Inspection Pvt Ltd, Kolkata, IN | B320: Mauritius | C320: 1
A321: Cotecna India Inspection Pvt Ltd, Kolkata, IN | B321: Ireland | C321: 1
A322: PT Mutuagung Lestari, Depok, ID | B322: Indonesia | C322: 45
A323: PT Mutuagung Lestari, Depok, ID | B323: Malaysia | C323: 20
... A339: Normec QS BV, Ede, NL | B339: Switzerland | C339: 1
A340: Normec QS BV, Ede, NL | C340: 0
A341: Normec QS BV, Ede, NL | C341: 0
A342: Baltic Control Certification, Albertslund, DK | B342: Denmark | C342: 47
A343: Baltic Control Certification, Albertslund, DK | B343: Bulgaria | C343: 14
A344: Baltic Control Certification, Albertslund, DK | B344: Ukraine | C344: 10
A345: Baltic Control Certification, Albertslund, DK | B345: Singapore | C345: 4
A346: Baltic Control Certification, Albertslund, DK | B346: Norway | C346: 4
A347: Baltic Control Certification, Albertslund, DK | B347: Spain | C347: 2
A348: Baltic Control Certification, Albertslund, DK | B348: Switzerland | C348: 2
A349: Baltic Control Certification, Albertslund, DK | B349: Taiwan (Province of China) | C349: 1
A350: Baltic Control Certification, Albertslund, DK | B350: The United States of America | C350: 1
A351: Baltic Control Certification, Albertslund, DK | B351: Sweden | C351: 1
A352: TÜV SÜD Czech s.r.o., Praha 4, CZ | B352: Czech Republic | C352: 79
A353: TÜV SÜD Czech s.r.o., Praha 4, CZ | B353: Slovakia | C353: 8
... A355: TÜV SÜD Czech s.r.o., Praha 4, CZ | B355: Hungary | C355: 1
A356: TÜV SÜD Czech s.r.o., Praha 4, CZ | C356: 0
A357: TÜV SÜD Czech s.r.o., Praha 4, CZ | C357: 0
A358: TÜV SÜD Czech s.r.o., Praha 4, CZ | C358: 0
A359: TÜV SÜD Czech s.r.o., Praha 4, CZ | C359: 0
A360: TÜV SÜD Czech s.r.o., Praha 4, CZ | C360: 0
A361: TÜV SÜD Czech s.r.o., Praha 4, CZ | C361: 0
A362: Baltic Control Certification, Risskov, DK | B362: Denmark | C362: 51
A363: Baltic Control Certification, Risskov, DK | B363: Norway | C363: 5
A364: Baltic Control Certification, Risskov, DK | B364: Bulgaria | C364: 4
A365: Baltic Control Certification, Risskov, DK | B365: Ukraine | C365: 4
A366: Baltic Control Certification, Risskov, DK | B366: United States | C366: 4
A367: Baltic Control Certification, Risskov, DK | B367: United Arab Emirates | C367: 3
...

Sheet Country_List
A1: China
A2: United States
A3: Indonesia
A4: Italy
A5: Malaysia
A6: Spain
A7: Germany
A8: Japan
A9: Netherlands
A10: Singapore
A11: France
A12: United Kingdom
... A146: Unknown

Sheet CB_List
A1: SGS Germany GmbH, Emstek, DE
A2: Control Union Certifications Germany GmbH, Berlin, DE
A3: SCS Global Services, Emeryville, CA, US
A4: RINA Services S.p.A., Genova, IT
A5: Bureau Veritas Polska Sp. z o.o., Warsaw, PL
A6: Control Union Poland Sp. z o.o., Zielona Gora, PL
A7: PT Intertek Utama Services, Jakarta, ID
A8: BM Certification, Riga, LV
A9: Trans Certification and Inspection Sdn Bhd, Kuantan, MY
A10: PT. Qualitas Sertifikasi Indonesia, Jakarta, ID
A11: DNV Business Assurance Sweden AB, Solna, SE
A12: DEKRA Certification B.V., Arnhem, NL
... A72: LSQA, Montevideo, UY

Sheet Country Summary
A1: Country | B1: Active Certificates
A2: China | B2: 2200
A3: United States | B3: 971
A4: Indonesia | B4: 881
A5: Italy | B5: 881
A6: Malaysia | B6: 748
A7: Spain | B7: 709
A8: Germany | B8: 675
A9: Japan | B9: 627
A10: Netherlands | B10: 469
A11: Singapore | B11: 468
A12: France | B12: 440
A13: United Kingdom | B13: 386
... A147: Unknown | B147: 1

Sheet Data
A1: Client Name | B1: Scope | C1: Issuing CB | D1: Expiry Date | E1: Country
A2: Harima USA,Inc., DULUTH, The United States of America | B2: Collecting Point, Trader with Storage | C2: SCS Global Services, Emeryville, CA, US | D2: 06.08.2027 | E2: The United States of America
A3: RA Energy Biofuels GmbH, Luzern, Switzerland | B3: Trader | C3: Control Union Certifications Germany GmbH, Berlin, DE | D3: 06.08.2027 | E3: Switzerland
A4: Harima USA,Inc., DULUTH, The United States of America | B4: Collecting Point, Trader with Storage | C4: SCS Global Services, Emeryville, CA, US | D4: 06.08.2027 | E4: The United States of America
A5: KEM ONE, Balan, France | B5: Processing Unit | C5: Bureau Veritas Polska Sp. z o.o., Warsaw, PL | D5: 06.08.2027 | E5: France
A6: INNOVIA Films Poland, Płock, Poland | B6: Processing Unit | C6: Control Union Poland Sp. z o.o., Zielona Gora, PL | D6: 06.08.2027 | E6: Poland
A7: Repsol Trading S.A., Community of Madrid, Spain | B7: Trader with Storage | C7: Control Union Poland Sp. z o.o., Zielona Gora, PL | D7: 06.08.2027 | E7: Spain
A8: Repsol Trading S.A., Community of Madrid, Spain | B8: Trader with Storage | C8: Control Union Poland Sp. z o.o., Zielona Gora, PL | D8: 06.08.2027 | E8: Spain
A9: Repsol Trading S.A., Community of Madrid, Spain | B9: Proof of Compliance Trader, Trader with Storage | C9: Control Union Poland Sp. z o.o., Zielona Gora, PL | D9: 06.08.2027 | E9: Spain
A10: AXPO Solutions AG, Baden, Switzerland | B10: Trader | C10: DEKRA Certification GmbH, Stuttgart, DE | D10: 06.08.2027 | E10: Switzerland
A11: PT. Anugerah Sawit Sejahtera, Kab. Kampar, Indonesia | B11: Point of Origin | C11: RINA Services S.p.A., Genova, IT | D11: 06.08.2027 | E11: Indonesia
A12: Toray Carbon Fibers Europe, LACQ, France | B12: Processing Unit | C12: Bureau Veritas Polska Sp. z o.o., Warsaw, PL | D12: 06.08.2027 | E12: France
... A16323: Ladang Petri Tenggara (Kilang Sawit Sg Kachur), Bandar Tenggara, Malaysia | B16323: Point of Origin | C16323: Trans Certification and Inspection Sdn Bhd, Kuantan, MY | D16323: 07.08.2026 | E16323: Malaysia
A16324: NS Millennium Vietnam Company Limited, Bau Bang District, Binh Duong, | B16324: Processing Unit | C16324: Trans Certification and Inspection Sdn Bhd, Kuantan, MY | D16324: 07.08.2026
A16325: Laizhou Tongji Chemical Co.,Ltd, Laizhou, China | B16325: Processing Unit, Collecting Point | C16325: PT Intertek Utama Services, Jakarta, ID | D16325: 07.08.2026 | E16325: China
A16326: FGV PALM INDUSTRIES, MUKIM TRIANG, BERA, Malaysia | B16326: Point of Origin | C16326: Trans Certification and Inspection Sdn Bhd, Kuantan, MY | D16326: 07.08.2026 | E16326: Malaysia
